jules_mcp/__init__.py
jules_mcp/__main__.py
jules_mcp/jules_mcp.py
jules_mcp/py.typed
jules_mcp-0.1.6.dist-info/licenses/LICENSE
tests/test_jules_mcp/__init__.py
tests/test_jules_mcp/conftest.py
tests/test_jules_mcp/test_mcp_server.py
jules_mcp-0.1.6.dist-info/METADATA
jules_mcp-0.1.6.dist-info/WHEEL
jules_mcp-0.1.6.dist-info/top_level.txt
jules_mcp-0.1.6.dist-info/RECORD
