Metadata-Version: 2.4
Name: jules-mcp
Version: 0.1.6
Summary: Google Jules MCP server
Author-email: Yurii Serhiichuk <savik@gmail.com>
License-Expression: Apache-2.0
Project-URL: homepage, https://github.com/CodeAgentBridge/jules-mcp-server
Project-URL: source, https://github.com/CodeAgentBridge/jules-mcp-server.git
Project-URL: issues, https://github.com/CodeAgentBridge/jules-mcp-server/issues
Project-URL: releasenotes, https://github.com/CodeAgentBridge/jules-mcp-server/releases
Project-URL: container, https://github.com/CodeAgentBridge/jules-mcp-server/pkgs/container/jules-mcp-server
Keywords: jules,mcp,google
Requires-Python: >=3.13
License-File: LICENSE
Requires-Dist: fastmcp>=2.12.4
Requires-Dist: jules-agent-sdk>=0.1.1
Requires-Dist: requests>=2.32.5
Dynamic: license-file
